enamel/__init__.py
enamel/enamel.py
enamelware-0.0.1.dist-info/LICENCE
enamelware-0.0.1.dist-info/METADATA
enamelware-0.0.1.dist-info/WHEEL
enamelware-0.0.1.dist-info/top_level.txt
enamelware-0.0.1.dist-info/RECORD
