Metadata-Version: 2.1
Name: enamelware
Version: 0.0.1
Summary: Enamelware - a simple application framework
Home-page: https://github.com/sinoia
Author: John Allen
Author-email: allen.john.e@gmail.com
License: UNKNOWN
Platform: UNKNOWN
Classifier: Programming Language :: Python :: 3
Classifier: License :: OSI Approved :: MIT License
Classifier: Operating System :: OS Independent
Requires-Python: >=3.6
